[
  {
    "id": "c4683601-4052-4296-9787-18dcf07944f4",
    "data": [
      {
        "text": "海事處",
        "meta": "@General_MarineDept",
        "alias": "general_marinedept",
        "userDefined": false
      }
    ],
    "isTemplate": false,
    "count": 1,
    "lang": "zh-hk",
    "updated": 0
  },
  {
    "id": "4b78f4a2-29a9-4b2b-a101-61870ede234c",
    "data": [
      {
        "text": "海事部門",
        "meta": "@General_MarineDept",
        "alias": "general_marinedept",
        "userDefined": false
      }
    ],
    "isTemplate": false,
    "count": 0,
    "lang": "zh-hk",
    "updated": 0
  },
  {
    "id": "1a77c53d-c5ad-4b8a-bc73-b1db0b28d2ab",
    "data": [
      {
        "text": "航海部門",
        "meta": "@General_MarineDept",
        "alias": "general_marinedept",
        "userDefined": false
      }
    ],
    "isTemplate": false,
    "count": 0,
    "lang": "zh-hk",
    "updated": 0
  },
  {
    "id": "0a19140d-d6dc-4c21-9aa1-ff2c15541910",
    "data": [
      {
        "text": "Sea Department",
        "meta": "@General_MarineDept",
        "alias": "general_marinedept",
        "userDefined": false
      }
    ],
    "isTemplate": false,
    "count": 0,
    "lang": "zh-hk",
    "updated": 0
  },
  {
    "id": "ffddb236-ef9f-474d-a557-ba1d6f9c4371",
    "data": [
      {
        "text": "Marine Department",
        "meta": "@General_MarineDept",
        "alias": "general_marinedept",
        "userDefined": false
      }
    ],
    "isTemplate": false,
    "count": 0,
    "lang": "zh-hk",
    "updated": 0
  }
]